primosmarcos/__init__.py
primosmarcos-1.1.dist-info/LICENSE
primosmarcos-1.1.dist-info/METADATA
primosmarcos-1.1.dist-info/WHEEL
primosmarcos-1.1.dist-info/top_level.txt
primosmarcos-1.1.dist-info/RECORD
