Metadata-Version: 2.1
Name: primosmarcos
Version: 1.1
Summary: Herramientas que permiten saber si un número es primo y un listado de 1 a n.
Home-page: UNKNOWN
Author: Marcos Cortés
Author-email: mcortesu@gmail.com
License: GNU GPLv3
Keywords: primos mathematical operations
Platform: UNKNOWN
Classifier: Development Status :: 4 - Beta
Classifier: Intended Audience :: Developers
Classifier: Topic :: Utilities
Classifier: License :: OSI Approved :: GNU General Public License v3 (GPLv3)
Classifier: Programming Language :: Python :: 3
Classifier: Operating System :: OS Independent
